brute/__init__.py
brute/brute.py
brute_force_attacker-1.0.1.dist-info/METADATA
brute_force_attacker-1.0.1.dist-info/WHEEL
brute_force_attacker-1.0.1.dist-info/entry_points.txt
brute_force_attacker-1.0.1.dist-info/top_level.txt
brute_force_attacker-1.0.1.dist-info/RECORD
