Metadata-Version: 2.1
Name: brute-force-attacker
Version: 1.0.1
Summary: A wrapper tool for mediainfo tool
Author: Praveen
Author-email: mspraveenkumar77@gmail.com
Requires-Dist: beautifulsoup4 ==4.12.2
Requires-Dist: bs4 ==0.0.1
Requires-Dist: certifi ==2023.11.17
Requires-Dist: charset-normalizer ==3.3.2
Requires-Dist: idna ==3.6
Requires-Dist: requests ==2.31.0
Requires-Dist: soupsieve ==2.5
Requires-Dist: termcolor ==2.4.0
Requires-Dist: urllib3 ==2.1.0
